cache/counter_m.v

/*
  Total = 8, c5 = 1, c10 = 2
*/

module counter_m (clk, reset, money, End, ch, out);

  input 	       clk, reset;
  input [2:0] money;
  output End, ch;
  output [1:0] out;

  reg [3:0] count;
  reg End,ch;
  wire [3:0] result;
  
  always @(posedge clk, posedge reset)
  begin
    if ( reset )  count <= 4'b0000;
    else count <= count + money;
  end 

  always @(count)
  begin
    End = 0; ch = 0;
    if ( count >= 4'b1000 ) End = 1;
    if ( count >  4'b1000 ) ch = 1;
  end

  assign result = count -4'b1000;
  assign out = result[1:0];
 
endmodule // counter

cache/fsm_m.v
module fsm_m (clk, reset,End , ch , done, chout, rst);
input clk, reset, End, ch;
output done, chout, rst;

reg done, chout, rst;

reg [1:0] state;

parameter Initial = 2'b00, Count = 2'b01, Done = 2'b10, Change = 2'b11;

/* State register (synchronous reset) */
always @(posedge clk or posedge reset) 
begin
  if (reset) 
    state <= Initial;
  else 
    case (state)
    Initial: 
      state <= Count;
    Count: 
      if (End && !ch)  state <= Done;
      else if (End && ch ) state <= Change;
      else state <= Count;
    Done: 
      state <= Initial;
    Change: 
      state <= Initial;    
  endcase
end

/* Output logic */
always @(*) begin
  rst = (state == Initial); 
  done = (state == Done || state == Change);
  chout = (state == Change);
end

endmodule

machine/top_machine.v
module machine(
clk, reset, c5, c10, c20, done, change
);
input clk;
input reset;
input c5,c10,c20;
output done;
output [1:0] change;


wire [2:0] money;

assign money = (c20) ? 3'b100 :
               (c10) ? 3'b010 : 
               (c5) ? 3'b001:3'b000; 

wire End, ch, chout;
wire [1:0] Change;
wire  rst;

fsm_m FSM (.clk (clk), .reset (reset),.End (End) , .ch (ch), .done(done), .chout (chout), .rst(rst));

counter_m Cnt (.clk(clk), .reset(rst), .money(money), .End(End), .ch(ch), .out(Change));

assign change = (chout)?Change: 2'b00;

endmodule

cache/machine_tb.v
// iverilog -o my_design top_machine.v counter_m.v fsm_m.v machine_tb.v
/*
Then run it:

vvp my_design

Then look at the test.vcd waveform:

gtkwave test.vcd & 
*/
module test;

  /* Make a reset that pulses once. */
  reg reset = 0;
  reg c5 = 0;
  reg c10 = 0;
  reg c20 = 0;

  initial begin
     $dumpfile("test.vcd");
    $dumpvars(0,test);
     # 2 reset = 1;
     # 2 reset = 0;
     # 2 c5 =1;
     # 2 c5 = 0;
     # 0 c10 = 1;
     # 4 c10 = 0;
     # 4 c5 = 1;
     # 4 c5 = 0;
     # 2 c20 = 1;
     # 2 c20 = 0;
     # 6 c20 = 1;
     # 4 c20 = 0;
     # 10 $finish;
  end

  /* Make a regular pulsing clock. */
  reg clk = 0;
  always #1 clk = !clk;

  wire [1:0] change;
  wire done;

 machine m(
.clk(clk), .reset(reset), .c5(c5), .c10(c10), .c20(c20), .done(done), .change(change)
);

  initial
     $monitor("At time %t, change = %0d  done = %0d",
              $time, change, done);
endmodule // test

cache/test.vcd
$date
	Sun Oct  1 20:06:13 2017
$end
$version
	Icarus Verilog
$end
$timescale
	1s
$end
$scope module test $end
$var wire 2 ! change [1:0] $end
$var wire 1 " done $end
$var reg 1 # c10 $end
$var reg 1 $ c20 $end
$var reg 1 % c5 $end
$var reg 1 & clk $end
$var reg 1 ' reset $end
$scope module m $end
$var wire 2 ( Change [1:0] $end
$var wire 1 ) End $end
$var wire 1 * c10 $end
$var wire 1 + c20 $end
$var wire 1 , c5 $end
$var wire 1 - ch $end
$var wire 2 . change [1:0] $end
$var wire 1 / chout $end
$var wire 1 0 clk $end
$var wire 1 " done $end
$var wire 3 1 money [2:0] $end
$var wire 1 2 reset $end
$var wire 1 3 rst $end
$scope module FSM $end
$var wire 1 ) End $end
$var wire 1 - ch $end
$var wire 1 0 clk $end
$var wire 1 2 reset $end
$var reg 1 4 chout $end
$var reg 1 5 done $end
$var reg 1 6 rst $end
$var reg 2 7 state [1:0] $end
$upscope $end
$scope module Cnt $end
$var wire 1 0 clk $end
$var wire 3 8 money [2:0] $end
$var wire 2 9 out [1:0] $end
$var wire 1 3 reset $end
$var wire 4 : result [3:0] $end
$var reg 1 ; End $end
$var reg 1 < ch $end
$var reg 4 = count [3:0] $end
$upscope $end
$upscope $end
$upscope $end
$enddefinitions $end
#0
$dumpvars
bx =
x<
x;
bx :
bx 9
b0 8
bx 7
x6
x5
x4
x3
02
b0 1
00
x/
bx .
x-
0,
0+
0*
x)
bx (
0'
0&
0%
0$
0#
x"
bx !
$end
#1
1&
10
#2
0<
0-
0;
0)
b0 (
b0 9
b0 =
b1000 :
b0 !
b0 .
04
0/
05
0"
16
13
b0 7
0&
00
1'
12
#3
1&
10
#4
0&
00
0'
02
#5
06
03
b1 7
1&
10
#6
b1 1
b1 8
0&
00
1%
1,
#7
b1 (
b1 9
b1 =
b1001 :
1&
10
#8
b10 1
b10 8
1#
1*
0&
00
0%
0,
#9
b11 (
b11 9
b11 =
b1011 :
1&
10
#10
0&
00
#11
b1 (
b1 9
b101 =
b1101 :
1&
10
#12
b0 1
b0 8
0&
00
0#
0*
#13
1&
10
#14
0&
00
#15
1&
10
#16
b1 1
b1 8
0&
00
1%
1,
#17
b10 (
b10 9
b110 =
b1110 :
1&
10
#18
0&
00
#19
b11 (
b11 9
b111 =
b1111 :
1&
10
#20
b0 1
b0 8
0&
00
0%
0,
#21
1&
10
#22
b100 1
b100 8
0&
00
1$
1+
#23
1<
1-
1;
1)
b1011 =
b11 :
1&
10
#24
b0 1
b0 8
0&
00
0$
0+
#25
b11 !
b11 .
14
1/
15
1"
b11 7
1&
10
#26
0&
00
#27
0<
0-
0;
0)
b0 (
b0 9
b0 =
b1000 :
b0 !
b0 .
04
0/
05
0"
16
13
b0 7
1&
10
#28
0&
00
#29
06
03
b1 7
1&
10
#30
b100 1
b100 8
0&
00
1$
1+
#31
b100 =
b1100 :
1&
10
#32
0&
00
#33
1;
1)
b1000 =
b0 :
1&
10
#34
b0 1
b0 8
0&
00
0$
0+
#35
15
1"
b10 7
1&
10
#36
0&
00
#37
0;
0)
b0 =
b1000 :
05
0"
16
13
b0 7
1&
10
#38
0&
00
#39
06
03
b1 7
1&
10
